helpmepick/__init__.py
helpmepick/main.py
helpmepick/models/__init__.py
helpmepick/models/champion.py
helpmepick/models/pool.py
helpmepick/models/region.py
helpmepick/models/role.py
helpmepick/models/tier.py
helpmepick/persistence/__init__.py
helpmepick/persistence/base.py
helpmepick/persistence/csv.py
helpmepick/pool/__init__.py
helpmepick/pool/base.py
helpmepick/pool/yaml.py
helpmepick/services/__init__.py
helpmepick/services/opgg.py
helpmepick/utils/throttler.py
helpmepick-0.1.9.dist-info/METADATA
helpmepick-0.1.9.dist-info/WHEEL
helpmepick-0.1.9.dist-info/entry_points.txt
helpmepick-0.1.9.dist-info/RECORD
